easyaudit/__init__.py
easyaudit/admin.py
easyaudit/admin_helpers.py
easyaudit/apps.py
easyaudit/backends.py
easyaudit/crudhistory_admin_mixin.py
easyaudit/locale/de/LC_MESSAGES/django.mo
easyaudit/locale/de/LC_MESSAGES/django.po
easyaudit/locale/fr/LC_MESSAGES/django.mo
easyaudit/locale/fr/LC_MESSAGES/django.po
easyaudit/locale/ru/LC_MESSAGES/django.mo
easyaudit/locale/ru/LC_MESSAGES/django.po
easyaudit/middleware/__init__.py
easyaudit/middleware/easyaudit.py
easyaudit/migrations/0001_initial.py
easyaudit/migrations/0002_externalservicelog_remove_crudevent_user_and_more.py
easyaudit/migrations/__init__.py
easyaudit/models.py
easyaudit/protocols.py
easyaudit/serializers.py
easyaudit/settings.py
easyaudit/signals/__init__.py
easyaudit/signals/auth_signals.py
easyaudit/signals/crud_flows.py
easyaudit/signals/model_signals.py
easyaudit/signals/request_signals.py
easyaudit/tasks.py
easyaudit/templates/admin/easyaudit/change_list.html
easyaudit/templates/admin/easyaudit/purge_confirmation.html
easyaudit/utils.py
easyaudit_clickhouse-0.1.0.dist-info/LICENSE
easyaudit_clickhouse-0.1.0.dist-info/METADATA
easyaudit_clickhouse-0.1.0.dist-info/WHEEL
easyaudit_clickhouse-0.1.0.dist-info/RECORD
